Metadata-Version: 2.1
Name: WifiScannerPro
Version: 0.0.2
Summary: A Simple Wifi Scanner With connected Isp Routers
Home-page: https://github.com/Tonmoy-abc/WifiScanner/
Author: Mahmudul Hahan Tonmoy
Author-email: playerandgamertonmoy@gmail.com
License: MIT
Keywords: ip scanner,wifi scanner,wifi password,show wifi password,wifi password hacker,wifi hacker,
Platform: UNKNOWN
Classifier: Development Status :: 5 - Production/Stable
Classifier: Intended Audience :: Education
Classifier: Operating System :: Microsoft :: Windows
Classifier: Operating System :: POSIX :: Linux
Classifier: License :: OSI Approved :: MIT License
Classifier: Programming Language :: Python :: 3
Requires-Python: >=3.6
